COPYING.md
MANIFEST.in
README.rst
example.toml
setup.cfg
setup.py
cpg/__init__.py
cpg/__main__.py
cpg/cli.py
cpg/groups.py
cpg/playlist.py
cpg/settings.py
cpg/tag.py
cpg.egg-info/PKG-INFO
cpg.egg-info/SOURCES.txt
cpg.egg-info/dependency_links.txt
cpg.egg-info/entry_points.txt
cpg.egg-info/requires.txt
cpg.egg-info/top_level.txt
docs/Makefile
docs/conf.py
docs/index.rst
docs/installation.rst
docs/usage.rst