Metadata-Version: 1.2
Name: cpg
Version: 0.1.0
Summary: A configurable playlist generator
Home-page: https://gitlab.com/9f/cpg
Author: Claudio Kozický
Author-email: koziccla@fit.cvut.cz
License: GNU GPLv3
Platform: UNKNOWN
Classifier: Development Status :: 2 - Pre-Alpha
Classifier: Environment :: Console
Classifier: License :: OSI Approved :: GNU General Public License v3 (GPLv3)
Classifier: Operating System :: POSIX :: Linux
Classifier: Programming Language :: Python
Classifier: Programming Language :: Python :: 3.6
Classifier: Programming Language :: Python :: 3 :: Only
Requires-Python: ~=3.6
